blindfile/__init__.py
blindfile-0.1.1.dist-info/WHEEL
blindfile-0.1.1.dist-info/entry_points.txt
blindfile-0.1.1.dist-info/METADATA
blindfile-0.1.1.dist-info/RECORD
