Metadata-Version: 2.3
Name: blindfile
Version: 0.1.1
Summary: The virtual blindfold to make truly unbiased file comparisons
Keywords: file,comparison,blind,testing
Author: Jerzy Kowalski
Author-email: Jerzy Kowalski <kowalskijerzy@aol.com>
License: MIT
Classifier: Development Status :: 4 - Beta
Classifier: Environment :: Console
Classifier: Intended Audience :: Developers
Classifier: Programming Language :: Python :: 3
Classifier: Programming Language :: Python :: 3.13
Requires-Dist: pydantic>=2.12.0
Requires-Dist: randomname>=0.2.1
Requires-Dist: typer>=0.19.2
Requires-Python: >=3.13
Project-URL: Homepage, https://github.com/jurekkow/blindfile
Project-URL: Repository, https://github.com/jurekkow/blindfile
